casbin_postgresql_watcher-1.4.0.dist-info/licenses/LICENSE
postgresql_watcher/__init__.py
postgresql_watcher/casbin_channel_subscription.py
postgresql_watcher/watcher.py
casbin_postgresql_watcher-1.4.0.dist-info/METADATA
casbin_postgresql_watcher-1.4.0.dist-info/WHEEL
casbin_postgresql_watcher-1.4.0.dist-info/top_level.txt
casbin_postgresql_watcher-1.4.0.dist-info/RECORD
