Metadata-Version: 2.4
Name: casbin-postgresql-watcher
Version: 1.4.0
Summary: Casbin role watcher to be used for monitoring updates to policies for PyCasbin
Home-page: https://github.com/officialpycasbin/postgresql-watcher
Author: hsluoyz
Author-email: hsluoyz@gmail.com
Classifier: Programming Language :: Python :: 3.9
Classifier: Programming Language :: Python :: 3.10
Classifier: Programming Language :: Python :: 3.11
Classifier: Programming Language :: Python :: 3.12
Classifier: License :: OSI Approved :: Apache Software License
Classifier: Operating System :: OS Independent
License-File: LICENSE
Requires-Dist: pycasbin>=2.0.0
Requires-Dist: psycopg2-binary>=2.8.6
Provides-Extra: dev
Requires-Dist: black==24.4.2; extra == "dev"
Dynamic: author
Dynamic: author-email
Dynamic: classifier
Dynamic: description
Dynamic: description-content-type
Dynamic: home-page
Dynamic: license-file
Dynamic: provides-extra
Dynamic: requires-dist
Dynamic: summary
